LICENSE
unitestify.py
unitestify-0.1.0.dist-info/entry_points.txt
unitestify-0.1.0.dist-info/LICENSE
unitestify-0.1.0.dist-info/WHEEL
unitestify-0.1.0.dist-info/METADATA
unitestify-0.1.0.dist-info/RECORD
