Metadata-Version: 2.1
Name: unitestify
Version: 0.1.0
Summary: Base unittest scaffold package
Home-page: https://github.com/victory-sokolov/unitestify
License: MIT
Keywords: Django tests,unittests
Author: Viktor Sokolov
Author-email: viktorsokolov.and@gmail.com
Requires-Python: >=3.10,<4.0
Classifier: License :: OSI Approved :: MIT License
Classifier: Programming Language :: Python :: 3
Classifier: Programming Language :: Python :: 3.10
Classifier: Programming Language :: Python :: 3.11
Requires-Dist: click (>=8.1.3,<9.0.0)
Project-URL: Repository, https://github.com/victory-sokolov/unitestify
